Metadata-Version: 2.1
Name: st-optics
Version: 0.1.2
Summary: Spatial-temporal OPTICS
Home-page: https://github.com/eren-ck/st_optics
Author: Eren Cakmak
Author-email: 22754816+eren-ck@users.noreply.github.com
License: License :: OSI Approved :: MIT License
Platform: any
Classifier: Development Status :: 4 - Beta
Classifier: Intended Audience :: Science/Research
Classifier: Intended Audience :: Developers
Classifier: License :: OSI Approved :: MIT License
Classifier: Programming Language :: Python
Classifier: Programming Language :: Python :: 3
Classifier: Programming Language :: Python :: 3.5
Classifier: Programming Language :: Python :: 3.6
Classifier: Programming Language :: Python :: 3.7
Classifier: Topic :: Software Development
Classifier: Topic :: Scientific/Engineering
Classifier: Operating System :: Microsoft :: Windows
Classifier: Operating System :: Unix
Classifier: Operating System :: MacOS
Provides-Extra: testing
